tailk/__init__.py
tailk/constants.py
tailk/highlighter.py
tailk/main.py
tailk/tail.py
tailk-0.1.0.dist-info/LICENSE
tailk-0.1.0.dist-info/WHEEL
tailk-0.1.0.dist-info/entry_points.txt
tailk-0.1.0.dist-info/METADATA
tailk-0.1.0.dist-info/RECORD
