Metadata-Version: 2.1
Name: tailk
Version: 0.1.0
Summary: Tail kubernetes pods logs
Home-page: https://github.com/ffaraone/tailk
License: Apache-2.0
Keywords: tail,log,kubernetes,pods
Author: Francesco Faraone
Author-email: ffaraone@gmail.com
Requires-Python: >=3.8,<4
Classifier: Development Status :: 5 - Production/Stable
Classifier: Environment :: Console
Classifier: Intended Audience :: Developers
Classifier: Intended Audience :: System Administrators
Classifier: License :: OSI Approved :: Apache Software License
Classifier: Operating System :: MacOS
Classifier: Operating System :: POSIX :: Linux
Classifier: Programming Language :: Python :: 3
Classifier: Programming Language :: Python :: 3.8
Classifier: Programming Language :: Python :: 3.9
Classifier: Programming Language :: Python :: 3.10
Classifier: Programming Language :: Python :: 3.11
Classifier: Programming Language :: Python :: 3.10
Classifier: Programming Language :: Python :: 3.11
Classifier: Programming Language :: Python :: 3.8
Classifier: Programming Language :: Python :: 3.9
Classifier: Topic :: Utilities
Requires-Dist: click (>=8.1.3,<9.0.0)
Requires-Dist: rich (>=13.2.0,<14.0.0)
Requires-Dist: uvloop (>=0.17.0,<0.18.0)
Project-URL: Repository, https://github.com/ffaraone/tailk
